[
 {
   "Frq.": "438.950 \n144.5125",
   "CTCSS": "-",
   "RPT Network": "EchoLink \nNode: 28304",
   "RPT's": "S55UCE-R",
   "QTH": "Gora \n(Celje)",
   "LOC": "JN76OH",
   "ASL": "554m",
   "DTMF short": "B1",
   "Owner": "S51KQ",
   "Sysop": "S51KQ"
 },
 {
   "Frq.": "145.650 \n145 050",
   "CTCSS": "71.9 \n88.5",
   "RPT Network": "EchoLink \nNode: 28870",
   "RPT's": "S55VXX-R",
   "QTH": "Maribor",
   "LOC": "JN76TN",
   "ASL": "290m",
   "DTMF short": "B2",
   "Owner": "S59DXX \nS56WAN",
   "Sysop": "S56WAN \nS52HI \nS51UL"
 },
 {
   "Frq.": "439.125 \n145.5875",
   "CTCSS": "-",
   "RPT Network": "EchoLink \nNode: 47093 \nTemp. OFF",
   "RPT's": "S55UTR-R",
   "QTH": "Planina \n(Trbovlje)",
   "LOC": "JN76ME",
   "ASL": "1011m",
   "DTMF short": "B3",
   "Owner": "S56CT",
   "Sysop": "S56CT"
 },
 {
   "Frq.": "145.225",
   "CTCSS": "-",
   "RPT Network": "EchoLink \nNode: 124137",
   "RPT's": "S50EDX-L",
   "QTH": "Cerkno",
   "LOC": "JN66XD",
   "ASL": "324m",
   "DTMF short": "B4",
   "Owner": "S50E",
   "Sysop": "S50U \nS51J"
 },
 {
   "Frq.": "145.700 \n145 100",
   "CTCSS": "67.0",
   "RPT Network": "EchoLink \nNode: 167520",
   "RPT's": "S55VCE-R",
   "QTH": "Mrzlica",
   "LOC": "JN76NE",
   "ASL": "1127m",
   "DTMF short": "B5",
   "Owner": "S59DOR",
   "Sysop": "S59DOR"
 },
 {
   "Frq.": "144.550",
   "CTCSS": "88.5",
   "RPT Network": "EchoLink \nNode: 216136",
   "RPT's": "S55VZR-L",
   "QTH": "Ljubljana",
   "LOC": "JN76GB",
   "ASL": "300m",
   "DTMF short": "B6",
   "Owner": "S56WZM \nS56CT",
   "Sysop": "S56WZM \nS56CT"
 },
 {
   "Frq.": "145.6875 \n145 0875",
   "CTCSS": "77.0",
   "RPT Network": "EchoLink \nNode: 260597",
   "RPT's": "S55VZV-R \n(s56zab)",
   "QTH": "Zagarski vrh",
   "LOC": "JN76IA",
   "ASL": "626m",
   "DTMF short": "B7",
   "Owner": "S53DZZ",
   "Sysop": "S56ZAB"
 },
 {
   "Frq.": "145.7875 \n145.1875",
   "CTCSS": "-",
   "RPT Network": "EchoLink \nNode: 315147",
   "RPT's": "S55VTO-R",
   "QTH": "Kanin",
   "LOC": "JN66RI",
   "ASL": "2180m",
   "DTMF short": "B8",
   "Owner": "S59DAP",
   "Sysop": "S51SA"
 },
 {
   "Frq.": "439.000",
   "CTCSS": "-",
   "RPT Network": "EchoLink \nNode: 316250",
   "RPT's": "S55USE-R",
   "QTH": "Laze \n(Sevnica)",
   "LOC": "JN75PX",
   "ASL": "528m",
   "DTMF short": "B9",
   "Owner": "S56CT",
   "Sysop": "S56CT"
 },
 {
   "Frq.": "",
   "CTCSS": "",
   "RPT Network": "",
   "RPT's": "",
   "QTH": "",
   "LOC": "",
   "ASL": "",
   "DTMF short": "",
   "Owner": "",
   "Sysop": ""
 },
 {
   "Frq.": "",
   "CTCSS": "",
   "RPT Network": "EchoLink \nTemporary \nshortcuts to foreign repeaters for visitors in Slovenia",
   "RPT's": "xxxxx-R",
   "QTH": "",
   "LOC": "",
   "ASL": "",
   "DTMF short": "C1 \nvalid till xx.xx.2005",
   "Owner": "",
   "Sysop": "-"
 }
]